{"BaseModel.68309be6-8340-4d3d-9a5c-2f36d40ff955": {"id": "68309be6-8340-4d3d-9a5c-2f36d40ff955", "created_at": "2022-07-05T22:20:35.661329", "updated_at": "2022-07-05T22:20:35.661346", "name": "My_First_Model", "my_number": 89, "__class__": "BaseModel"}, "BaseModel.bd60dbde-3531-4e53-8007-abc158020eeb": {"id": "bd60dbde-3531-4e53-8007-abc158020eeb", "created_at": "2022-07-05T22:24:59.473736", "updated_at": "2022-07-05T22:24:59.473820", "name": "My First Model", "my_number": 89, "__class__": "BaseModel"}, "BaseModel.d7e94a9c-1f0d-4d55-960b-a4ff0bcf861f": {"id": "d7e94a9c-1f0d-4d55-960b-a4ff0bcf861f", "created_at": "2022-07-05T22:26:49.103781", "updated_at": "2022-07-05T22:26:49.103864", "name": "My First Model", "my_number": 89, "__class__": "BaseModel"}, "BaseModel.f1ca77bb-59d8-4131-967e-2c01baaac62f": {"id": "f1ca77bb-59d8-4131-967e-2c01baaac62f", "created_at": "2022-07-05T22:28:26.885618", "updated_at": "2022-07-05T22:28:26.885690", "name": "My First Model", "my_number": 89, "__class__": "BaseModel"}}